[{ "_id" : "23wAavpWNJEN2GQNK", "parent" : "_root", "fieldName" : null, "specifiedType" : "_token", "type" : "_token", "typecheckError" : null, "isObject" : true, "objectName" : "Department", "formula" : null, "children" : [ "WysgtEr7PFu3sQ3AS", "SCmMFXtsxsZzYAfKG", "ZkpYTDFY84pKvkpnN" ] },{ "_id" : "2k8m88o66Z2Srgm9R", "parent" : "JWWx62xng6gx9hvR8", "fieldName" : "rateNT", "specifiedType" : null, "type" : "number", "typecheckError" : null, "isObject" : false, "objectName" : null, "formula" : [ "*", [ "down", [ "var", "this" ], "cReKDb5jERxxMcRH9", null, true ], [ "down", [ "filter", [ "down", [ "down", [ "up", [ "var", "this" ], "RA8ggdsAwcAMyw8qv", false ], "seqtnxA6pxNAjq9g3", null, true ], "vfKTTY6pRM7asvz5Y", null, false ], [ "e", [ "=", [ "down", [ "var", "e" ], "EM2R2ZT3zFN5jgsoo", null, true ], [ "down", [ "var", "this" ], "LXwCbsjwz2btXPC7n", null, true ] ] ] ], "qnc8hzBps7Xt2Jk72", null, true ] ], "children" : [], "display" : null },{ "_id" : "2mhoAd7kgb277rDJm", "parent" : "ZkpYTDFY84pKvkpnN", "fieldName" : null, "specifiedType" : "_token", "type" : "_token", "typecheckError" : null, "isObject" : true, "objectName" : "ProjectInfo", "formula" : null, "children" : [ "BER3bsepaPt7nbKuH", "A8Jyn89BEHYLBFvvL", "q3kJCRFmJgmnyebNW", "uK2XNYcaezbJujKXk" ] },{ "_id" : "2njK8bcNfwtaHCRq5", "parent" : "_root", "fieldName" : null, "specifiedType" : "_token", "type" : "_token", "typecheckError" : null, "isObject" : true, "objectName" : "Period", "formula" : null, "children" : [ "xtaPkDgrTMJqnBbA3" ] },{ "_id" : "3HDDF9NMGatu6NzeJ", "parent" : "uK2XNYcaezbJujKXk", "fieldName" : "costNT", "specifiedType" : null, "type" : "number", "typecheckError" : null, "isObject" : false, "objectName" : null, "formula" : [ "sum", [ "down", [ "var", "this" ], "guMhAjzenNiicLcvC", null, false ], [ "se", [ "down", [ "var", "se" ], "zEx6kWxRaAAdjCn46", null, true ] ] ], "children" : [], "display" : null },{ "_id" : "3pqpSHWFgCMDSJR9v", "parent" : "uK2XNYcaezbJujKXk", "fieldName" : "division", "specifiedType" : "6tGYx9EBBFFD7R9Hk", "type" : "6tGYx9EBBFFD7R9Hk", "typecheckError" : null, "isObject" : false, "objectName" : null, "formula" : null, "children" : [], "display" : null },{ "_id" : "6tGYx9EBBFFD7R9Hk", "parent" : "RA8ggdsAwcAMyw8qv", "fieldName" : null, "specifiedType" : "_token", "type" : "_token", "typecheckError" : null, "isObject" : true, "objectName" : "Division", "formula" : null, "children" : [ "cjJmjqvSri9tXhjGh" ] },{ "_id" : "7LBorjeGBGNNjvJRm", "parent" : "guMhAjzenNiicLcvC", "fieldName" : "role", "specifiedType" : "Waddb7SnpwFAJ33Gh", "type" : "Waddb7SnpwFAJ33Gh", "typecheckError" : null, "isObject" : false, "objectName" : null, "formula" : null, "children" : [], "display" : null },{ "_id" : "A8Jyn89BEHYLBFvvL", "parent" : "2mhoAd7kgb277rDJm", "fieldName" : "effort", "specifiedType" : null, "type" : "number", "typecheckError" : null, "isObject" : false, "objectName" : null, "formula" : [ "sum", [ "down", [ "var", "this" ], "uK2XNYcaezbJujKXk", null, false ], [ "dsi", [ "down", [ "var", "dsi" ], "GGrejfc2PGsFesDDj", null, true ] ] ], "children" : [], "display" : null },{ "_id" : "BER3bsepaPt7nbKuH", "parent" : "2mhoAd7kgb277rDJm", "fieldName" : "project", "specifiedType" : "SCmMFXtsxsZzYAfKG", "type" : "SCmMFXtsxsZzYAfKG", "typecheckError" : null, "isObject" : false, "objectName" : null, "formula" : null, "children" : [], "display" : null },{ "_id" : "CAbvcbjXk2XeDjS7X", "parent" : "ZkpYTDFY84pKvkpnN", "fieldName" : "costNT", "specifiedType" : null, "type" : "number", "typecheckError" : null, "isObject" : false, "objectName" : null, "formula" : [ "sum", [ "down", [ "var", "this" ], "2mhoAd7kgb277rDJm", null, false ], [ "pi", [ "down", [ "var", "pi" ], "q3kJCRFmJgmnyebNW", null, true ] ] ], "children" : [], "display" : null },{ "_id" : "EM2R2ZT3zFN5jgsoo", "parent" : "vfKTTY6pRM7asvz5Y", "fieldName" : "period", "specifiedType" : "2njK8bcNfwtaHCRq5", "type" : "2njK8bcNfwtaHCRq5", "typecheckError" : null, "isObject" : false, "objectName" : null, "formula" : null, "children" : [], "display" : null },{ "_id" : "EYd8xJqernG9LiGP9", "parent" : "_root", "fieldName" : null, "specifiedType" : "_token", "type" : "_token", "typecheckError" : null, "isObject" : true, "objectName" : "Employee", "formula" : null, "children" : [ "JJK4vvLNpriMcozwX" ] },{ "_id" : "FoXdSavcoYjfAEu7G", "parent" : "ZkpYTDFY84pKvkpnN", "fieldName" : "site", "specifiedType" : null, "type" : "RA8ggdsAwcAMyw8qv", "typecheckError" : null, "isObject" : true, "objectName" : "SiteTotals", "formula" : [ "up", [ "down", [ "var", "this" ], "Nafd8ArJF8WzZLPaG", null, true ], "RA8ggdsAwcAMyw8qv", false ], "children" : [ "z6pvPZL2PZvHX29Tk" ], "display" : null },{ "_id" : "GGrejfc2PGsFesDDj", "parent" : "uK2XNYcaezbJujKXk", "fieldName" : "effort", "specifiedType" : null, "type" : "number", "typecheckError" : null, "isObject" : false, "objectName" : null, "formula" : [ "sum", [ "down", [ "var", "this" ], "guMhAjzenNiicLcvC", null, false ], [ "se", [ "down", [ "var", "se" ], "S859QZN8Q9oAy4wFJ", null, true ] ] ], "children" : [], "display" : null },{ "_id" : "JJK4vvLNpriMcozwX", "parent" : "EYd8xJqernG9LiGP9", "fieldName" : "name", "specifiedType" : "text", "type" : "text", "typecheckError" : null, "isObject" : false, "objectName" : null, "formula" : null, "children" : [], "display" : null },{ "_id" : "JWWx62xng6gx9hvR8", "parent" : "RA8ggdsAwcAMyw8qv", "fieldName" : null, "specifiedType" : "_token", "type" : "_token", "typecheckError" : null, "isObject" : true, "objectName" : "Quotation", "formula" : null, "children" : [ "LXwCbsjwz2btXPC7n", "cReKDb5jERxxMcRH9", "2k8m88o66Z2Srgm9R" ], "display" : null },{ "_id" : "LWXmKdCTxa9Qogkxw", "parent" : "guMhAjzenNiicLcvC", "fieldName" : "employee", "specifiedType" : "EYd8xJqernG9LiGP9", "type" : "EYd8xJqernG9LiGP9", "typecheckError" : null, "isObject" : false, "objectName" : null, "formula" : null, "children" : [], "display" : null },{ "_id" : "LXwCbsjwz2btXPC7n", "parent" : "JWWx62xng6gx9hvR8", "fieldName" : "period", "specifiedType" : "2njK8bcNfwtaHCRq5", "type" : "2njK8bcNfwtaHCRq5", "typecheckError" : null, "isObject" : false, "objectName" : null, "formula" : null, "children" : [], "display" : null },{ "_id" : "LpKErbDJuvFMBTeK5", "parent" : "Waddb7SnpwFAJ33Gh", "fieldName" : "name", "specifiedType" : "text", "type" : "text", "typecheckError" : null, "isObject" : false, "objectName" : null, "formula" : null, "children" : [], "display" : null },{ "_id" : "Nafd8ArJF8WzZLPaG", "parent" : "ZkpYTDFY84pKvkpnN", "fieldName" : "division", "specifiedType" : null, "type" : "6tGYx9EBBFFD7R9Hk", "typecheckError" : null, "isObject" : true, "objectName" : "DivTotals", "formula" : [ "down", [ "down", [ "down", [ "var", "this" ], "2mhoAd7kgb277rDJm", null, false ], "uK2XNYcaezbJujKXk", null, false ], "3pqpSHWFgCMDSJR9v", null, true ], "children" : [ "p6FfsBEkc42TCRbc8", "ynoaZpjNwbZXQaxvt", "vzo3sdp6LkWekMheH" ], "display" : null },{ "_id" : "NjrKMtFz6kmJmMdLN", "parent" : "ZkpYTDFY84pKvkpnN", "fieldName" : "period", "specifiedType" : "2njK8bcNfwtaHCRq5", "type" : "2njK8bcNfwtaHCRq5", "typecheckError" : null, "isObject" : false, "objectName" : null, "formula" : null, "children" : [], "display" : null },{ "_id" : "RA8ggdsAwcAMyw8qv", "parent" : "_root", "fieldName" : null, "specifiedType" : "_token", "type" : "_token", "typecheckError" : null, "isObject" : true, "objectName" : "Site", "formula" : null, "children" : [ "wgdEQzfE5Et9YxtTJ", "seqtnxA6pxNAjq9g3", "JWWx62xng6gx9hvR8", "6tGYx9EBBFFD7R9Hk" ] },{ "_id" : "RJrhjw7JaPWQTDbLo", "parent" : "guMhAjzenNiicLcvC", "fieldName" : "activities", "specifiedType" : "text", "type" : "text", "typecheckError" : null, "isObject" : false, "objectName" : null, "formula" : null, "children" : [], "display" : null },{ "_id" : "S859QZN8Q9oAy4wFJ", "parent" : "guMhAjzenNiicLcvC", "fieldName" : "effort", "specifiedType" : "number", "type" : "number", "typecheckError" : null, "isObject" : false, "objectName" : null, "formula" : null, "children" : [], "display" : null },{ "_id" : "SCmMFXtsxsZzYAfKG", "parent" : "23wAavpWNJEN2GQNK", "fieldName" : null, "specifiedType" : "_token", "type" : "_token", "typecheckError" : null, "isObject" : true, "objectName" : "Project", "formula" : null, "children" : [ "gNkaaqqnEYRTCgBx2" ] },{ "_id" : "Waddb7SnpwFAJ33Gh", "parent" : "_root", "fieldName" : null, "specifiedType" : "_token", "type" : "_token", "typecheckError" : null, "isObject" : true, "objectName" : "Role", "formula" : null, "children" : [ "LpKErbDJuvFMBTeK5" ] },{ "_id" : "WysgtEr7PFu3sQ3AS", "parent" : "23wAavpWNJEN2GQNK", "fieldName" : "name", "specifiedType" : "text", "type" : "text", "typecheckError" : null, "isObject" : false, "objectName" : null, "formula" : null, "children" : [], "display" : null },{ "_id" : "YCdREWzTS522Hs6ec", "parent" : "eh3kSchuYr5MbcBM2", "fieldName" : "name", "specifiedType" : "text", "type" : "text", "typecheckError" : null, "isObject" : false, "objectName" : null, "formula" : null, "children" : [], "display" : null },{ "_id" : "ZkpYTDFY84pKvkpnN", "parent" : "23wAavpWNJEN2GQNK", "fieldName" : null, "specifiedType" : "_token", "type" : "_token", "typecheckError" : null, "isObject" : true, "objectName" : "PeriodInfo", "formula" : null, "children" : [ "NjrKMtFz6kmJmMdLN", "CAbvcbjXk2XeDjS7X", "2mhoAd7kgb277rDJm", "Nafd8ArJF8WzZLPaG", "FoXdSavcoYjfAEu7G" ] },{ "_id" : "_root", "children" : [ "23wAavpWNJEN2GQNK", "2njK8bcNfwtaHCRq5", "EYd8xJqernG9LiGP9", "Waddb7SnpwFAJ33Gh", "RA8ggdsAwcAMyw8qv", "eh3kSchuYr5MbcBM2" ], "fieldName" : null, "specifiedType" : "_token", "type" : "_token", "typecheckError" : null, "isObject" : true, "objectName" : null, "formula" : null },{ "_id" : "cReKDb5jERxxMcRH9", "parent" : "JWWx62xng6gx9hvR8", "fieldName" : "rateLocal", "specifiedType" : "number", "type" : "number", "typecheckError" : null, "isObject" : false, "objectName" : null, "formula" : null, "children" : [] },{ "_id" : "cjJmjqvSri9tXhjGh", "parent" : "6tGYx9EBBFFD7R9Hk", "fieldName" : "name", "specifiedType" : "text", "type" : "text", "typecheckError" : null, "isObject" : false, "objectName" : null, "formula" : null, "children" : [], "display" : null },{ "_id" : "eh3kSchuYr5MbcBM2", "parent" : "_root", "fieldName" : null, "specifiedType" : "_token", "type" : "_token", "typecheckError" : null, "isObject" : true, "objectName" : "Currency", "formula" : null, "children" : [ "YCdREWzTS522Hs6ec", "vfKTTY6pRM7asvz5Y" ] },{ "_id" : "gNkaaqqnEYRTCgBx2", "parent" : "SCmMFXtsxsZzYAfKG", "fieldName" : "name", "specifiedType" : "text", "type" : "text", "typecheckError" : null, "isObject" : false, "objectName" : null, "formula" : null, "children" : [], "display" : null },{ "_id" : "guMhAjzenNiicLcvC", "parent" : "uK2XNYcaezbJujKXk", "fieldName" : null, "specifiedType" : "_token", "type" : "_token", "typecheckError" : null, "isObject" : true, "objectName" : "SupportEntry", "formula" : null, "children" : [ "7LBorjeGBGNNjvJRm", "LWXmKdCTxa9Qogkxw", "S859QZN8Q9oAy4wFJ", "zEx6kWxRaAAdjCn46", "RJrhjw7JaPWQTDbLo" ] },{ "_id" : "p6FfsBEkc42TCRbc8", "parent" : "Nafd8ArJF8WzZLPaG", "fieldName" : "dsis", "specifiedType" : null, "type" : "uK2XNYcaezbJujKXk", "typecheckError" : null, "isObject" : false, "objectName" : null, "formula" : [ "filter", [ "down", [ "down", [ "up", [ "var", "this" ], "ZkpYTDFY84pKvkpnN", false ], "2mhoAd7kgb277rDJm", null, false ], "uK2XNYcaezbJujKXk", null, false ], [ "dsi", [ "=", [ "down", [ "var", "dsi" ], "3pqpSHWFgCMDSJR9v", null, true ], [ "up", [ "var", "this" ], "Nafd8ArJF8WzZLPaG", true ] ] ] ], "children" : [], "display" : null },{ "_id" : "q3kJCRFmJgmnyebNW", "parent" : "2mhoAd7kgb277rDJm", "fieldName" : "costNT", "specifiedType" : null, "type" : "number", "typecheckError" : null, "isObject" : false, "objectName" : null, "formula" : [ "sum", [ "down", [ "var", "this" ], "uK2XNYcaezbJujKXk", null, false ], [ "dsi", [ "down", [ "var", "dsi" ], "3HDDF9NMGatu6NzeJ", null, true ] ] ], "children" : [], "display" : null },{ "_id" : "qnc8hzBps7Xt2Jk72", "parent" : "vfKTTY6pRM7asvz5Y", "fieldName" : "toNT", "specifiedType" : "number", "type" : "number", "typecheckError" : null, "isObject" : false, "objectName" : null, "formula" : null, "children" : [] },{ "_id" : "seqtnxA6pxNAjq9g3", "parent" : "RA8ggdsAwcAMyw8qv", "fieldName" : "currency", "specifiedType" : "eh3kSchuYr5MbcBM2", "type" : "eh3kSchuYr5MbcBM2", "typecheckError" : null, "isObject" : false, "objectName" : null, "formula" : null, "children" : [], "display" : null },{ "_id" : "uK2XNYcaezbJujKXk", "parent" : "2mhoAd7kgb277rDJm", "fieldName" : null, "specifiedType" : "_token", "type" : "_token", "typecheckError" : null, "isObject" : true, "objectName" : "ProjDivSupportInfo", "formula" : null, "children" : [ "3pqpSHWFgCMDSJR9v", "GGrejfc2PGsFesDDj", "3HDDF9NMGatu6NzeJ", "guMhAjzenNiicLcvC" ] },{ "_id" : "vfKTTY6pRM7asvz5Y", "parent" : "eh3kSchuYr5MbcBM2", "fieldName" : null, "specifiedType" : "_token", "type" : "_token", "typecheckError" : null, "isObject" : true, "objectName" : "ExchangeRateEntry", "formula" : null, "children" : [ "EM2R2ZT3zFN5jgsoo", "qnc8hzBps7Xt2Jk72" ] },{ "_id" : "vzo3sdp6LkWekMheH", "parent" : "Nafd8ArJF8WzZLPaG", "fieldName" : "costNT", "specifiedType" : null, "type" : "number", "typecheckError" : null, "isObject" : false, "objectName" : null, "formula" : [ "sum", [ "down", [ "var", "this" ], "p6FfsBEkc42TCRbc8", null, true ], [ "dsi", [ "down", [ "var", "dsi" ], "3HDDF9NMGatu6NzeJ", null, true ] ] ], "children" : [], "display" : null },{ "_id" : "wgdEQzfE5Et9YxtTJ", "parent" : "RA8ggdsAwcAMyw8qv", "fieldName" : "name", "specifiedType" : "text", "type" : "text", "typecheckError" : null, "isObject" : false, "objectName" : null, "formula" : null, "children" : [], "display" : null },{ "_id" : "xtaPkDgrTMJqnBbA3", "parent" : "2njK8bcNfwtaHCRq5", "fieldName" : "month", "specifiedType" : "text", "type" : "text", "typecheckError" : null, "isObject" : false, "objectName" : null, "formula" : null, "children" : [], "display" : null },{ "_id" : "ynoaZpjNwbZXQaxvt", "parent" : "Nafd8ArJF8WzZLPaG", "fieldName" : "effort", "specifiedType" : null, "type" : "number", "typecheckError" : null, "isObject" : false, "objectName" : null, "formula" : [ "sum", [ "down", [ "var", "this" ], "p6FfsBEkc42TCRbc8", null, true ], [ "dsi", [ "down", [ "var", "dsi" ], "GGrejfc2PGsFesDDj", null, true ] ] ], "children" : [], "display" : null },{ "_id" : "z6pvPZL2PZvHX29Tk", "parent" : "FoXdSavcoYjfAEu7G", "fieldName" : "costNT", "specifiedType" : null, "type" : "number", "typecheckError" : null, "isObject" : false, "objectName" : null, "formula" : [ "sum", [ "filter", [ "down", [ "up", [ "var", "this" ], "ZkpYTDFY84pKvkpnN", false ], "Nafd8ArJF8WzZLPaG", null, false ], [ "dt", [ "=", [ "up", [ "up", [ "var", "dt" ], "Nafd8ArJF8WzZLPaG", true ], "RA8ggdsAwcAMyw8qv", false ], [ "up", [ "var", "this" ], "FoXdSavcoYjfAEu7G", true ] ] ] ], [ "dt", [ "down", [ "var", "dt" ], "vzo3sdp6LkWekMheH", null, true ] ] ], "children" : [], "display" : null },{ "_id" : "zEx6kWxRaAAdjCn46", "parent" : "guMhAjzenNiicLcvC", "fieldName" : "costNT", "specifiedType" : null, "type" : "number", "typecheckError" : null, "isObject" : false, "objectName" : null, "formula" : [ "*", [ "down", [ "var", "this" ], "S859QZN8Q9oAy4wFJ", null, true ], [ "down", [ "filter", [ "down", [ "up", [ "down", [ "up", [ "var", "this" ], "uK2XNYcaezbJujKXk", false ], "3pqpSHWFgCMDSJR9v", null, true ], "RA8ggdsAwcAMyw8qv", false ], "JWWx62xng6gx9hvR8", null, false ], [ "q", [ "=", [ "down", [ "var", "q" ], "LXwCbsjwz2btXPC7n", null, true ], [ "down", [ "up", [ "var", "this" ], "ZkpYTDFY84pKvkpnN", false ], "NjrKMtFz6kmJmMdLN", null, true ] ] ] ], "2k8m88o66Z2Srgm9R", null, true ] ], "children" : [], "display" : null }]
